README.md
setup.py
TSofa.egg-info/PKG-INFO
TSofa.egg-info/SOURCES.txt
TSofa.egg-info/dependency_links.txt
TSofa.egg-info/entry_points.txt
TSofa.egg-info/requires.txt
TSofa.egg-info/top_level.txt
tsofa/__init__.py
tsofa/utils.py
tsofa/views/__init__.py
tsofa/views/_base.py
tsofa/views/_base_cmd.py
tsofa/views/_base_dy.py
tsofa/views/sdocs/__init__.py
tsofa/views/sdocs/_base.py
tsofa/views/sdocs/dy.py
tsofa/views/sdocs/hr.py
tsofa/views/sdocs/mn.py
tsofa/views/sdocs/sc.py
tsofa/views/sdocs/cmds/__init__.py
tsofa/views/sdocs/cmds/_base.py
tsofa/views/sdocs/cmds/dy.py
tsofa/views/sdocs/cmds/hr.py
tsofa/views/sdocs/cmds/mn.py
tsofa/views/sdocs/cmds/sc.py
tsofa/views/snums/__init__.py
tsofa/views/snums/_base.py
tsofa/views/snums/dy.py
tsofa/views/snums/hr.py
tsofa/views/snums/mn.py
tsofa/views/snums/sc.py
tsofa/views/snums/cmds/__init__.py
tsofa/views/snums/cmds/_base.py
tsofa/views/snums/cmds/dy.py
tsofa/views/snums/cmds/hr.py
tsofa/views/snums/cmds/mn.py
tsofa/views/snums/cmds/sc.py
tsofa/views/sobjs/__init__.py
tsofa/views/sobjs/dy.py
tsofa/views/sobjs/hr.py
tsofa/views/sobjs/mn.py
tsofa/views/sobjs/sc.py
tsofa/views/sobjs/cmds/__init__.py
tsofa/views/sobjs/cmds/dy.py
tsofa/views/sobjs/cmds/hr.py
tsofa/views/sobjs/cmds/mn.py
tsofa/views/sobjs/cmds/sc.py
tsofa/views/svals/__init__.py
tsofa/views/svals/dy.py
tsofa/views/svals/hr.py
tsofa/views/svals/mn.py
tsofa/views/svals/sc.py
tsofa/views/svals/cmds/__init__.py
tsofa/views/svals/cmds/dy.py
tsofa/views/svals/cmds/hr.py
tsofa/views/svals/cmds/mn.py
tsofa/views/svals/cmds/sc.py