Metadata-Version: 1.1
Name: TSofa
Version: 0.1
Summary: This package contains the reference CouchDB views for well formatted timeseries data, the Python functionality to retrieve data from those views, and functionality to process the output.
Home-page: https://bitbucket.org/notequal/tsofa/
Author: Stanley Engle
Author-email: stan.engle@gmail.com
License: BSD License
Platform: UNKNOWN
Classifier: Development Status :: 5 - Production/Stable
Classifier: Environment :: Web Environment
Classifier: Intended Audience :: End Users/Desktop
Classifier: Intended Audience :: Science/Research
Classifier: License :: OSI Approved :: BSD License
Classifier: Natural Language :: English
Classifier: Operating System :: OS Independent
Classifier: Programming Language :: Python
Classifier: Programming Language :: Python :: 3.6
Classifier: Programming Language :: Python :: 3.7
Classifier: Topic :: Internet :: WWW/HTTP
Classifier: Topic :: Internet :: WWW/HTTP :: Dynamic Content
